neatnet/__init__.py
neatnet/artifacts.py
neatnet/continuity.py
neatnet/gaps.py
neatnet/geometry.py
neatnet/nodes.py
neatnet/simplify.py
neatnet/tests/conftest.py
neatnet/tests/test_artifacts.py
neatnet/tests/test_continuity.py
neatnet/tests/test_gaps.py
neatnet/tests/test_geometry.py
neatnet/tests/test_nodes.py
neatnet/tests/test_simplify.py
neatnet/tests/data/apalachicola_original.parquet
neatnet/tests/data/apalachicola_simplified_exclusion_mask.parquet
neatnet/tests/data/apalachicola_simplified_standard.parquet
neatnet-0.1.3.dist-info/licenses/LICENSE
neatnet-0.1.3.dist-info/METADATA
neatnet-0.1.3.dist-info/WHEEL
neatnet-0.1.3.dist-info/top_level.txt
neatnet-0.1.3.dist-info/RECORD
