Metadata-Version: 2.4
Name: neatnet
Version: 0.1.3
Summary: Street geometry processing toolkit
Author-email: Martin Fleischmann <martin@martinfleischmann.net>, Anastassia Vybornova <anvy@itu.dk>, "James D. Gaboardi" <jgaboardi@gmail.com>
License: BSD 3-Clause
Project-URL: Home, https://github.com/uscuni/
Project-URL: Repository, https://github.com/uscuni/neatnet
Classifier: Programming Language :: Python :: 3
Classifier: License :: OSI Approved :: BSD License
Classifier: Operating System :: OS Independent
Classifier: Intended Audience :: Science/Research
Classifier: Topic :: Scientific/Engineering :: GIS
Requires-Python: >=3.11
License-File: LICENSE
Requires-Dist: esda>=2.6.0
Requires-Dist: geopandas>=1.0.1
Requires-Dist: libpysal>=4.12.1
Requires-Dist: momepy>=0.9.0
Requires-Dist: networkx>=3.3
Requires-Dist: numpy>=2
Requires-Dist: pandas>=2.2.3
Requires-Dist: scipy>=1.14.1
Requires-Dist: shapely>=2.0.6
Requires-Dist: scikit-learn>=1.2.0
Provides-Extra: tests
Requires-Dist: codecov; extra == "tests"
Requires-Dist: coverage; extra == "tests"
Requires-Dist: matplotlib; extra == "tests"
Requires-Dist: mypy<2,>=1.15.0; extra == "tests"
Requires-Dist: pre-commit; extra == "tests"
Requires-Dist: pyarrow>=17.0; extra == "tests"
Requires-Dist: pytest; extra == "tests"
Requires-Dist: pytest-cov; extra == "tests"
Requires-Dist: pytest-xdist; extra == "tests"
Requires-Dist: ruff; extra == "tests"
Requires-Dist: yamllint; extra == "tests"
Provides-Extra: docs
Requires-Dist: ipykernel; extra == "docs"
Requires-Dist: ipywidgets; extra == "docs"
Requires-Dist: jupyterlab; extra == "docs"
Requires-Dist: myst_nb; extra == "docs"
Requires-Dist: numpydoc; extra == "docs"
Requires-Dist: sphinx; extra == "docs"
Requires-Dist: sphinxcontrib-bibtex; extra == "docs"
Requires-Dist: sphinx_autosummary_accessors; extra == "docs"
Requires-Dist: sphinx_book_theme; extra == "docs"
Requires-Dist: sphinx_copybutton; extra == "docs"
Provides-Extra: all
Requires-Dist: neatnet[docs,tests]; extra == "all"
Dynamic: license-file
